ashtadhyayi_data/__init__.py
ashtadhyayi_data/correction/__init__.py
ashtadhyayi_data/correction/corrections.py
ashtadhyayi_data/correction/rephareplacer.py
ashtadhyayi_data/correction/issues/__init__.py
ashtadhyayi_data/correction/issues/6/__init__.py
ashtadhyayi_data/correction/issues/6/issue6.py
ashtadhyayi_data/correction/ngram/__init__.py
ashtadhyayi_data/correction/ngram/abnormngramscraper.py
ashtadhyayi_data/correction/ngram/nyasa_regen.py
ashtadhyayi_data/reader/__init__.py
ashtadhyayi_data/reader/ashtadhyayi_com/__init__.py
ashtadhyayi_data/reader/ashtadhyayi_com/dhaatu/__init__.py
ashtadhyayi_data/reader/ashtadhyayi_com/dhaatu/dict_maker.py
ashtadhyayi_data/reader/ashtadhyayi_com/suutra/__init__.py
ashtadhyayi_data/reader/ashtadhyayi_com/suutra/transformer.py
ashtadhyayi_data/reader/vritti_repo/__init__.py
ashtadhyayi_data/reader/vritti_tsv/__init__.py
ashtadhyayi_data/writer/__init__.py
ashtadhyayi_data/writer/babylon.py
ashtadhyayi_data-0.0.3.dist-info/LICENSE.txt
ashtadhyayi_data-0.0.3.dist-info/METADATA
ashtadhyayi_data-0.0.3.dist-info/WHEEL
ashtadhyayi_data-0.0.3.dist-info/top_level.txt
ashtadhyayi_data-0.0.3.dist-info/RECORD
