Metadata-Version: 2.1
Name: ashtadhyayi-data
Version: 0.0.3
Summary: A package for curating doc file collections, with ability to sync with youtube and archive.org doc items.
Home-page: https://github.com/ashtadhyayi/data_curation
Author: Sanskrit programmers
Author-email: sanskrit-programmers@googlegroups.com
License: MIT
Keywords: documents books internet-archive
Platform: UNKNOWN
Classifier: Development Status :: 5 - Production/Stable
Classifier: Intended Audience :: Education
Classifier: Topic :: Text Processing :: Linguistic
Classifier: License :: OSI Approved :: MIT License
Classifier: Programming Language :: Python :: 3
Classifier: Programming Language :: Python :: 3.7
License-File: LICENSE.txt
Requires-Dist: pandas
Requires-Dist: doc-curation
Requires-Dist: frontmatter
Provides-Extra: test
Requires-Dist: pytest ; extra == 'test'
